pystaad/__init__.py
pystaad/tools.py
pystaad-0.1.0.dist-info/LICENSE.md
pystaad-0.1.0.dist-info/METADATA
pystaad-0.1.0.dist-info/WHEEL
pystaad-0.1.0.dist-info/entry_points.txt
pystaad-0.1.0.dist-info/top_level.txt
pystaad-0.1.0.dist-info/RECORD
