Metadata-Version: 2.1
Name: pystaad
Version: 0.1.0
Summary: A Python package to simplify STAAD.Pro automation
Home-page: https://github.com/unrealweb01/pystaad
Author: Ragul
Author-email: testing010101@proton.me
Classifier: Programming Language :: Python :: 3
Classifier: License :: OSI Approved :: MIT License
Classifier: Operating System :: OS Independent
Requires-Python: >=3.7
License-File: LICENSE.md
Requires-Dist: pywin32 >=304
